rgbw_colorspace_converter/__init__.py
rgbw_colorspace_converter/randomcolor.py
rgbw_colorspace_converter/colors/__init__.py
rgbw_colorspace_converter/colors/converters.py
rgbw_colorspace_converter/colors/util/__init__.py
rgbw_colorspace_converter/colors/util/morph.py
rgbw_colorspace_converter/tools/__init__.py
rgbw_colorspace_converter/tools/color_printer.py
rgbw_colorspace_converter-0.1.3.data/scripts/path_between_2_colors.py
rgbw_colorspace_converter-0.1.3.data/scripts/print_colored_txt.py
rgbw_colorspace_converter-0.1.3.data/scripts/run_color_module_RGB_HSV_HEX_demo.py
rgbw_colorspace_converter-0.1.3.data/scripts/run_spectrum_saturation_cycler.py
rgbw_colorspace_converter-0.1.3.dist-info/LICENSE
rgbw_colorspace_converter-0.1.3.dist-info/METADATA
rgbw_colorspace_converter-0.1.3.dist-info/WHEEL
rgbw_colorspace_converter-0.1.3.dist-info/top_level.txt
rgbw_colorspace_converter-0.1.3.dist-info/RECORD
