Metadata-Version: 2.1
Name: rgbw-colorspace-converter
Version: 0.1.3
Summary: Convert between RGB / HSV / HSL / HSI / HEX Color Spaces. And, emit the RGBW code for each.
Home-page: https://github.com/iamh2o/rgbw_colorspace_converter
Author: John Major
Author-email: iamh2o@gmail.com
License: UNKNOWN
Project-URL: Bug Tracker, https://github.com/iamh2o/rgbw_colorspace_converter/issues
Platform: UNKNOWN
Classifier: Programming Language :: Python :: 3
Classifier: License :: OSI Approved :: MIT License
Classifier: Operating System :: OS Independent
Requires-Python: >=3.7
License-File: LICENSE
Requires-Dist: colr
Requires-Dist: docopt
Requires-Dist: html2image
Requires-Dist: ansi2html
